{
  "hash": "29b65f49",
  "configHash": "215bfe20",
  "lockfileHash": "54bb1a8d",
  "browserHash": "583c4571",
  "optimized": {
    "react": {
      "src": "../../node_modules/react/index.js",
      "file": "react.js",
      "fileHash": "55800cf0",
      "needsInterop": true
    },
    "react-dom/client": {
      "src": "../../node_modules/react-dom/client.js",
      "file": "react-dom_client.js",
      "fileHash": "448c2ecf",
      "needsInterop": true
    }
  },
  "chunks": {
    "chunk-B2WE2YPZ": {
      "file": "chunk-B2WE2YPZ.js"
    }
  }
}